charitybase/__init__.py
charitybase/clients.py
charitybase/core.py
charitybase/helpers.py
charity_base_client_python-0.1.3.dist-info/LICENSE
charity_base_client_python-0.1.3.dist-info/METADATA
charity_base_client_python-0.1.3.dist-info/WHEEL
charity_base_client_python-0.1.3.dist-info/top_level.txt
charity_base_client_python-0.1.3.dist-info/RECORD
