Metadata-Version: 2.1
Name: charity-base-client-python
Version: 0.1.3
Summary: A Python client library for interacting with the CharityBase REST API.
Home-page: https://github.com/drkane/charity-base-client-python
Author: David Kane
Author-email: david@drkane.co.uk
License: MIT
Platform: UNKNOWN
Classifier: Programming Language :: Python :: 3
Classifier: License :: OSI Approved :: MIT License
Classifier: Operating System :: OS Independent
Requires-Python: >=3
Requires-Dist: requests (==2.20.1)
